{
  "date": "2026-04-21",
  "data_sources": {
    "market_prices": "Yahoo Finance (yfinance)",
    "tw_margin": "FinMind API (TWSE OpenData)",
    "tw_institutional": "FinMind API (三大法人)",
    "scoring_method": "Rolling 252-day Z-score normalization",
    "behavioral_params": "Kahneman & Tversky (1979), Banerjee (1992)"
  },
  "us_market": {
    "SPY_close": 708.72,
    "SPY_RSI14": 97.7,
    "SPY_SMA20": 669.62,
    "SPY_SMA60": 676.93,
    "SPY_vs_52w_high_pct": 99.8,
    "SPY_5d_return_pct": 3.3,
    "SPY_20d_return_pct": 9.27,
    "VIX": 18.87,
    "US_10Y_yield": 4.25
  },
  "tw_market": {
    "TAIEX_close": 37678.0,
    "TAIEX_RSI14": 80.0,
    "TAIEX_SMA20": 34527.0,
    "TAIEX_vs_52w_high_pct": 100.0,
    "TAIEX_5d_return_pct": 3.81,
    "TAIEX_20d_return_pct": 12.33,
    "TSMC_close": 2065.0,
    "TSMC_vs_52w_high_pct": 99.0
  },
  "tw_retail_indicators": {
    "margin_balance": 8562532,
    "margin_5d_change_pct": 2.1,
    "margin_5d_trend": "INCREASING",
    "institutional_net_TWD": -25.3,
    "retail_net_est_TWD": 25.3,
    "foreign_net_TWD": 43.5,
    "foreign_consecutive_days": 1,
    "foreign_consecutive_direction": "buy",
    "TSMC_margin_balance": 26012,
    "TSMC_margin_30d_change_pct": 2.9
  },
  "jp_market": {
    "NIKKEI_close": 59546.76,
    "NIKKEI_RSI14": 74.0,
    "NIKKEI_SMA20": 55392.69,
    "NIKKEI_vs_52w_high_pct": 100.0,
    "NIKKEI_5d_return_pct": 2.88,
    "NIKKEI_20d_return_pct": 13.96,
    "jp_moodring_score": 94.1
  },
  "kr_market": {
    "KOSPI_close": 6356.09,
    "KOSPI_RSI14": 75.4,
    "KOSPI_SMA20": 5713.83,
    "KOSPI_vs_52w_high_pct": 100.0,
    "KOSPI_5d_return_pct": 6.51,
    "KOSPI_20d_return_pct": 14.44,
    "kr_moodring_score": 91.3
  },
  "eu_market": {
    "STOXX50_close": 5982.63,
    "STOXX50_RSI14": 73.7,
    "STOXX50_SMA20": 5754.38,
    "STOXX50_vs_52w_high_pct": 96.9,
    "STOXX50_5d_return_pct": 1.31,
    "STOXX50_20d_return_pct": 6.57,
    "eu_moodring_score": 81.6
  },
  "global_context": {
    "Gold": 4812.0,
    "USDJPY": 158.98,
    "USDTWD": 31.43
  }
}