{
  "date": "2026-04-08",
  "data_sources": {
    "market_prices": "Yahoo Finance (yfinance)",
    "tw_margin": "FinMind API (TWSE OpenData)",
    "tw_institutional": "FinMind API (三大法人)",
    "scoring_method": "Rolling 252-day Z-score normalization",
    "behavioral_params": "Kahneman & Tversky (1979), Banerjee (1992)"
  },
  "us_market": {
    "SPY_close": 673.63,
    "SPY_RSI14": 57.8,
    "SPY_SMA20": 656.57,
    "SPY_SMA60": 675.88,
    "SPY_vs_52w_high_pct": 97.1,
    "SPY_5d_return_pct": 3.58,
    "SPY_20d_return_pct": -0.25,
    "VIX": 21.63,
    "US_10Y_yield": 4.27
  },
  "tw_market": {
    "TAIEX_close": 34761.0,
    "TAIEX_RSI14": 55.1,
    "TAIEX_SMA20": 33292.0,
    "TAIEX_vs_52w_high_pct": 98.2,
    "TAIEX_5d_return_pct": 6.9,
    "TAIEX_20d_return_pct": 8.26,
    "TSMC_close": 1950.0,
    "TSMC_vs_52w_high_pct": 97.1
  },
  "tw_retail_indicators": {
    "margin_balance": 8141199,
    "margin_5d_change_pct": 0.91,
    "margin_5d_trend": "INCREASING",
    "institutional_net_TWD": 1583.6,
    "retail_net_est_TWD": -1583.6,
    "foreign_net_TWD": 1177.7,
    "foreign_consecutive_days": 2,
    "foreign_consecutive_direction": "buy",
    "TSMC_margin_balance": 26797,
    "TSMC_margin_30d_change_pct": 22.74
  },
  "jp_market": {
    "NIKKEI_close": 53429.56,
    "NIKKEI_RSI14": 49.1,
    "NIKKEI_SMA20": 53361.16,
    "NIKKEI_vs_52w_high_pct": 90.8,
    "NIKKEI_5d_return_pct": 4.63,
    "NIKKEI_20d_return_pct": 1.33,
    "jp_moodring_score": 85.7
  },
  "kr_market": {
    "KOSPI_close": null,
    "KOSPI_RSI14": 43.8,
    "KOSPI_SMA20": null,
    "KOSPI_vs_52w_high_pct": null,
    "KOSPI_5d_return_pct": null,
    "KOSPI_20d_return_pct": null,
    "kr_moodring_score": 67.6
  },
  "eu_market": {
    "STOXX50_close": 5898.83,
    "STOXX50_RSI14": 55.6,
    "STOXX50_SMA20": 5670.17,
    "STOXX50_vs_52w_high_pct": 95.6,
    "STOXX50_5d_return_pct": 6.44,
    "STOXX50_20d_return_pct": 3.76,
    "eu_moodring_score": 73.0
  },
  "global_context": {
    "Gold": 4774.0,
    "USDJPY": 158.28,
    "USDTWD": 31.72
  }
}